hodor_python/__init__.py
hodor_python/dataset.py
hodor_python-1.0.1.dist-info/WHEEL
hodor_python-1.0.1.dist-info/entry_points.txt
hodor_python-1.0.1.dist-info/METADATA
hodor_python-1.0.1.dist-info/RECORD
