Metadata-Version: 2.3
Name: hodor-python
Version: 1.0.1
Summary: Python API to access and download the HODOR dataset.
Requires-Dist: pandas>=2.3.2
Requires-Dist: pangaeapy>=1.1.0
Requires-Dist: requests>=2.32.5
Requires-Dist: tqdm>=4.67.1
Requires-Python: >=3.10
Project-URL: Homepage, https://github.com/gboeer/hodor_python
Project-URL: Issues, https://github.com/gboeer/hodor_python/issues
